Metadata-Version: 2.1
Name: optschedule
Version: 1.0.0
Summary: Flexible parameter scheduler that can be implemented with proprietary and open source optimizers and algorithms.
Home-page: https://github.com/draktr/optschedule
Author: draktr
License: MIT License
Project-URL: Documentation, https://optschedule.readthedocs.io/en/latest/
Project-URL: Issues, https://github.com/draktr/optschedule/issues
Keywords: schedule,optimization,decay,learning,parameters,training
Classifier: Development Status :: 4 - Beta
Classifier: Intended Audience :: Education
Classifier: Intended Audience :: Financial and Insurance Industry
Classifier: Intended Audience :: Healthcare Industry
Classifier: Intended Audience :: Science/Research
Classifier: License :: OSI Approved :: MIT License
Classifier: Operating System :: OS Independent
Classifier: Programming Language :: Python
Classifier: Topic :: Scientific/Engineering
Classifier: Topic :: Scientific/Engineering :: Artificial Intelligence
Classifier: Topic :: Scientific/Engineering :: Bio-Informatics
Classifier: Topic :: Scientific/Engineering :: Chemistry
Classifier: Topic :: Scientific/Engineering :: Mathematics
Classifier: Topic :: Scientific/Engineering :: Physics
Requires-Python: >=3.6
License-File: LICENSE
